ampersand/__init__.py
ampersand/ampersand.py
ampersand/build.py
ampersand/command_line.py
ampersand/handler.py
ampersand/templates/_ampersand.json
ampersand/templates/_plugin.json
ampersand/templates/page.json
ampersand-0.5.2.dist-info/DESCRIPTION.rst
ampersand-0.5.2.dist-info/METADATA
ampersand-0.5.2.dist-info/RECORD
ampersand-0.5.2.dist-info/WHEEL
ampersand-0.5.2.dist-info/entry_points.txt
ampersand-0.5.2.dist-info/metadata.json
ampersand-0.5.2.dist-info/top_level.txt
