Metadata-Version: 2.0
Name: ampersand
Version: 0.5.2
Summary: The really, really minimalistic static site generator
Home-page: http://github.com/natejms/ampersand
Author: Nathan Scott
Author-email: natejms@outlook.com
License: MIT
Keywords: ampersand amp static site generator localization globalization translation
Platform: UNKNOWN
Classifier: License :: OSI Approved :: MIT License
Classifier: Programming Language :: Python :: 3.6
Classifier: Intended Audience :: Developers
Classifier: Topic :: Internet
Classifier: Environment :: Console
Requires-Dist: future
Requires-Dist: pystache
